pytest_embedded_arduino/__init__.py
pytest_embedded_arduino/app.py
pytest_embedded_arduino/serial.py
pytest_embedded_arduino-2.6.0.dist-info/licenses/LICENSE
pytest_embedded_arduino-2.6.0.dist-info/WHEEL
pytest_embedded_arduino-2.6.0.dist-info/METADATA
pytest_embedded_arduino-2.6.0.dist-info/RECORD
